smiles_rnn-2.0.2.data/scripts/fine_tune.py
smiles_rnn-2.0.2.data/scripts/reinforcement_learning.py
smiles_rnn-2.0.2.data/scripts/sample_model.py
smiles_rnn-2.0.2.data/scripts/train_prior.py
smiles_rnn-2.0.2.dist-info/licenses/LICENSE
smilesrnn/RL.py
smilesrnn/__init__.py
smilesrnn/dataset.py
smilesrnn/gated_transformer.py
smilesrnn/rnn.py
smilesrnn/transformer.py
smilesrnn/utils.py
smilesrnn/vocabulary.py
smiles_rnn-2.0.2.dist-info/METADATA
smiles_rnn-2.0.2.dist-info/WHEEL
smiles_rnn-2.0.2.dist-info/top_level.txt
smiles_rnn-2.0.2.dist-info/RECORD
