Metadata-Version: 2.4
Name: SMILES-RNN
Version: 2.0.2
Summary: A scoring, benchmarking and evaluation framework for goal directed generative models
Author-email: Morgan Thomas <morganthomas263@gmail.com>
Project-URL: Homepage, https://github.com/MorganCThomas/SMILES-RNN
Project-URL: Issues, https://github.com/MorganCThomas/SMILES-RNN/issues
Keywords: SMILES,Chemical language models,De novo,Constrained de novo,chemistry,drug design,reinforcement learning
Classifier: Development Status :: 4 - Beta
Classifier: Programming Language :: Python :: 3
Classifier: Programming Language :: Python :: 3.6
Classifier: Programming Language :: Python :: 3.7
Classifier: Programming Language :: Python :: 3.8
Classifier: Programming Language :: Python :: 3.9
Classifier: Programming Language :: Python :: 3.10
Classifier: Programming Language :: Python :: 3.11
Classifier: Programming Language :: Python :: 3.12
Classifier: License :: OSI Approved :: MIT License
Classifier: Operating System :: OS Independent
Requires-Python: >=3.6
License-File: LICENSE
Requires-Dist: numpy
Requires-Dist: torch
Requires-Dist: deepsmiles
Requires-Dist: tensorboard
Requires-Dist: tqdm
Requires-Dist: deepsmiles
Requires-Dist: selfies
Requires-Dist: google-auth
Requires-Dist: promptsmiles
Dynamic: license-file
Dynamic: requires-dist
